{".class": "MypyFile", "_fullname": "zmq.eventloop._deprecated", "is_partial_stub_package": false, "is_stub": false, "names": {".class": "SymbolTable", "DelayedCallback": {".class": "SymbolTableNode", "kind": "Gdef", "node": {".class": "TypeInfo", "_promote": null, "abstract_attributes": [], "bases": ["zmq.eventloop.minitornado.ioloop.PeriodicCallback"], "declared_metaclass": null, "defn": {".class": "ClassDef", "fullname": "zmq.eventloop._deprecated.DelayedCallback", "name": "DelayedCallback", "type_vars": []}, "flags": [], "fullname": "zmq.eventloop._deprecated.DelayedCallback", "metaclass_type": null, "metadata": {}, "module_name": "zmq.eventloop._deprecated", "mro": ["zmq.eventloop._deprecated.DelayedCallback", "zmq.eventloop.minitornado.ioloop.PeriodicCallback", "builtins.object"], "names": {".class": "SymbolTable", "__init__": {".class": "SymbolTableNode", "kind": "Mdef", "node": {".class": "FuncDef", "arg_kinds": [0, 0, 0, 1], "arg_names": ["self", "callback", "callback_time", "io_loop"], "flags": [], "fullname": "zmq.eventloop._deprecated.DelayedCallback.__init__", "name": "__init__", "type": null}}, "_firstrun": {".class": "SymbolTableNode", "implicit": true, "kind": "Mdef", "node": {".class": "Var", "flags": [], "fullname": "zmq.eventloop._deprecated.DelayedCallback._firstrun", "name": "_firstrun", "type": {".class": "AnyType", "missing_import_name": null, "source_any": null, "type_of_any": 1}}}, "_run": {".class": "SymbolTableNode", "kind": "Mdef", "node": {".class": "FuncDef", "arg_kinds": [0], "arg_names": ["self"], "flags": [], "fullname": "zmq.eventloop._deprecated.DelayedCallback._run", "name": "_run", "type": null}}, "start": {".class": "SymbolTableNode", "kind": "Mdef", "node": {".class": "FuncDef", "arg_kinds": [0], "arg_names": ["self"], "flags": [], "fullname": "zmq.eventloop._deprecated.DelayedCallback.start", "name": "start", "type": null}}}, "tuple_type": null, "type_vars": [], "typeddict_type": null}}, "ETERM": {".class": "SymbolTableNode", "cross_ref": "zmq.sugar.constants.ETERM", "kind": "Gdef"}, "IOLoop": {".class": "SymbolTableNode", "kind": "Gdef", "node": {".class": "TypeAlias", "alias_tvars": [], "column": 0, "fullname": "zmq.eventloop._deprecated.IOLoop", "line": 196, "no_args": true, "normalized": false, "target": "zmq.eventloop._deprecated.ZMQIOLoop"}}, "POLLERR": {".class": "SymbolTableNode", "cross_ref": "zmq.sugar.constants.POLLERR", "kind": "Gdef"}, "POLLIN": {".class": "SymbolTableNode", "cross_ref": "zmq.sugar.constants.POLLIN", "kind": "Gdef"}, "POLLOUT": {".class": "SymbolTableNode", "cross_ref": "zmq.sugar.constants.POLLOUT", "kind": "Gdef"}, "PeriodicCallback": {".class": "SymbolTableNode", "cross_ref": "zmq.eventloop.minitornado.ioloop.PeriodicCallback", "kind": "Gdef"}, "PollIOLoop": {".class": "SymbolTableNode", "cross_ref": "zmq.eventloop.minitornado.ioloop.PollIOLoop", "kind": "Gdef"}, "Poller": {".class": "SymbolTableNode", "cross_ref": "zmq.sugar.poll.Poller", "kind": "Gdef"}, "Tuple": {".class": "SymbolTableNode", "cross_ref": "typing.Tuple", "kind": "Gdef"}, "ZMQError": {".class": "SymbolTableNode", "cross_ref": "zmq.error.ZMQError", "kind": "Gdef"}, "ZMQIOLoop": {".class": "SymbolTableNode", "kind": "Gdef", "node": {".class": "TypeInfo", "_promote": null, "abstract_attributes": [], "bases": ["zmq.eventloop.minitornado.ioloop.PollIOLoop"], "declared_metaclass": null, "defn": {".class": "ClassDef", "fullname": "zmq.eventloop._deprecated.ZMQIOLoop", "name": "ZMQIOLoop", "type_vars": []}, "flags": [], "fullname": "zmq.eventloop._deprecated.ZMQIOLoop", "metaclass_type": null, "metadata": {}, "module_name": "zmq.eventloop._deprecated", "mro": ["zmq.eventloop._deprecated.ZMQIOLoop", "zmq.eventloop.minitornado.ioloop.PollIOLoop", "zmq.eventloop.minitornado.ioloop.IOLoop", "zmq.eventloop.minitornado.util.Configurable", "builtins.object"], "names": {".class": "SymbolTable", "_zmq_impl": {".class": "SymbolTableNode", "kind": "Mdef", "node": {".class": "Var", "flags": ["is_initialized_in_class"], "fullname": "zmq.eventloop._deprecated.ZMQIOLoop._zmq_impl", "name": "_zmq_impl", "type": {".class": "CallableType", "arg_kinds": [], "arg_names": [], "arg_types": [], "bound_args": ["zmq.eventloop._deprecated.ZMQPoller"], "def_extras": {}, "fallback": "builtins.type", "implicit": true, "is_ellipsis_args": false, "name": null, "ret_type": "zmq.eventloop._deprecated.ZMQPoller", "type_guard": null, "variables": []}}}, "current": {".class": "SymbolTableNode", "kind": "Mdef", "node": {".class": "Decorator", "func": {".class": "FuncDef", "arg_kinds": [0, 2, 4], "arg_names": ["cls", "args", "kwargs"], "flags": ["is_class", "is_decorated"], "fullname": "zmq.eventloop._deprecated.ZMQIOLoop.current", "name": "current", "type": null}, "is_overload": false, "var": {".class": "Var", "flags": ["is_initialized_in_class", "is_classmethod", "is_ready"], "fullname": null, "name": "current", "type": {".class": "CallableType", "arg_kinds": [0, 2, 4], "arg_names": ["cls", "args", "kwargs"], "arg_types": [{".class": "TypeType", "item": "zmq.eventloop._deprecated.ZMQIOLoop"}, {".class": "AnyType", "missing_import_name": null, "source_any": null, "type_of_any": 1}, {".class": "AnyType", "missing_import_name": null, "source_any": null, "type_of_any": 1}], "bound_args": [], "def_extras": {}, "fallback": "builtins.function", "implicit": true, "is_ellipsis_args": false, "name": "current of ZMQIOLoop", "ret_type": {".class": "AnyType", "missing_import_name": null, "source_any": null, "type_of_any": 1}, "type_guard": null, "variables": []}}}}, "initialize": {".class": "SymbolTableNode", "kind": "Mdef", "node": {".class": "FuncDef", "arg_kinds": [0, 1, 4], "arg_names": ["self", "impl", "kwargs"], "flags": [], "fullname": "zmq.eventloop._deprecated.ZMQIOLoop.initialize", "name": "initialize", "type": null}}, "instance": {".class": "SymbolTableNode", "kind": "Mdef", "node": {".class": "Decorator", "func": {".class": "FuncDef", "arg_kinds": [0, 2, 4], "arg_names": ["cls", "args", "kwargs"], "flags": ["is_class", "is_decorated"], "fullname": "zmq.eventloop._deprecated.ZMQIOLoop.instance", "name": "instance", "type": null}, "is_overload": false, "var": {".class": "Var", "flags": ["is_initialized_in_class", "is_classmethod", "is_ready"], "fullname": null, "name": "instance", "type": {".class": "CallableType", "arg_kinds": [0, 2, 4], "arg_names": ["cls", "args", "kwargs"], "arg_types": [{".class": "TypeType", "item": "zmq.eventloop._deprecated.ZMQIOLoop"}, {".class": "AnyType", "missing_import_name": null, "source_any": null, "type_of_any": 1}, {".class": "AnyType", "missing_import_name": null, "source_any": null, "type_of_any": 1}], "bound_args": [], "def_extras": {}, "fallback": "builtins.function", "implicit": true, "is_ellipsis_args": false, "name": "instance of ZMQIOLoop", "ret_type": {".class": "AnyType", "missing_import_name": null, "source_any": null, "type_of_any": 1}, "type_guard": null, "variables": []}}}}, "start": {".class": "SymbolTableNode", "kind": "Mdef", "node": {".class": "FuncDef", "arg_kinds": [0], "arg_names": ["self"], "flags": [], "fullname": "zmq.eventloop._deprecated.ZMQIOLoop.start", "name": "start", "type": null}}}, "tuple_type": null, "type_vars": [], "typeddict_type": null}}, "ZMQPoller": {".class": "SymbolTableNode", "kind": "Gdef", "node": {".class": "TypeInfo", "_promote": null, "abstract_attributes": [], "bases": ["builtins.object"], "declared_metaclass": null, "defn": {".class": "ClassDef", "fullname": "zmq.eventloop._deprecated.ZMQPoller", "name": "ZMQPoller", "type_vars": []}, "flags": [], "fullname": "zmq.eventloop._deprecated.ZMQPoller", "metaclass_type": null, "metadata": {}, "module_name": "zmq.eventloop._deprecated", "mro": ["zmq.eventloop._deprecated.ZMQPoller", "builtins.object"], "names": {".class": "SymbolTable", "__init__": {".class": "SymbolTableNode", "kind": "Mdef", "node": {".class": "FuncDef", "arg_kinds": [0], "arg_names": ["self"], "flags": [], "fullname": "zmq.eventloop._deprecated.ZMQPoller.__init__", "name": "__init__", "type": null}}, "_map_events": {".class": "SymbolTableNode", "kind": "Mdef", "node": {".class": "Decorator", "func": {".class": "FuncDef", "arg_kinds": [0], "arg_names": ["events"], "flags": ["is_static", "is_decorated"], "fullname": "zmq.eventloop._deprecated.ZMQPoller._map_events", "name": "_map_events", "type": null}, "is_overload": false, "var": {".class": "Var", "flags": ["is_initialized_in_class", "is_staticmethod", "is_ready"], "fullname": null, "name": "_map_events", "type": {".class": "CallableType", "arg_kinds": [0], "arg_names": ["events"], "arg_types": [{".class": "AnyType", "missing_import_name": null, "source_any": null, "type_of_any": 1}], "bound_args": [], "def_extras": {}, "fallback": "builtins.function", "implicit": true, "is_ellipsis_args": false, "name": "_map_events of ZMQPoller", "ret_type": {".class": "AnyType", "missing_import_name": null, "source_any": null, "type_of_any": 1}, "type_guard": null, "variables": []}}}}, "_poller": {".class": "SymbolTableNode", "implicit": true, "kind": "Mdef", "node": {".class": "Var", "flags": [], "fullname": "zmq.eventloop._deprecated.ZMQPoller._poller", "name": "_poller", "type": {".class": "AnyType", "missing_import_name": null, "source_any": null, "type_of_any": 1}}}, "_remap_events": {".class": "SymbolTableNode", "kind": "Mdef", "node": {".class": "Decorator", "func": {".class": "FuncDef", "arg_kinds": [0], "arg_names": ["z_events"], "flags": ["is_static", "is_decorated"], "fullname": "zmq.eventloop._deprecated.ZMQPoller._remap_events", "name": "_remap_events", "type": null}, "is_overload": false, "var": {".class": "Var", "flags": ["is_initialized_in_class", "is_staticmethod", "is_ready"], "fullname": null, "name": "_remap_events", "type": {".class": "CallableType", "arg_kinds": [0], "arg_names": ["z_events"], "arg_types": [{".class": "AnyType", "missing_import_name": null, "source_any": null, "type_of_any": 1}], "bound_args": [], "def_extras": {}, "fallback": "builtins.function", "implicit": true, "is_ellipsis_args": false, "name": "_remap_events of ZMQPoller", "ret_type": {".class": "AnyType", "missing_import_name": null, "source_any": null, "type_of_any": 1}, "type_guard": null, "variables": []}}}}, "close": {".class": "SymbolTableNode", "kind": "Mdef", "node": {".class": "FuncDef", "arg_kinds": [0], "arg_names": ["self"], "flags": [], "fullname": "zmq.eventloop._deprecated.ZMQPoller.close", "name": "close", "type": null}}, "modify": {".class": "SymbolTableNode", "kind": "Mdef", "node": {".class": "FuncDef", "arg_kinds": [0, 0, 0], "arg_names": ["self", "fd", "events"], "flags": [], "fullname": "zmq.eventloop._deprecated.ZMQPoller.modify", "name": "modify", "type": null}}, "poll": {".class": "SymbolTableNode", "kind": "Mdef", "node": {".class": "FuncDef", "arg_kinds": [0, 0], "arg_names": ["self", "timeout"], "flags": [], "fullname": "zmq.eventloop._deprecated.ZMQPoller.poll", "name": "poll", "type": null}}, "register": {".class": "SymbolTableNode", "kind": "Mdef", "node": {".class": "FuncDef", "arg_kinds": [0, 0, 0], "arg_names": ["self", "fd", "events"], "flags": [], "fullname": "zmq.eventloop._deprecated.ZMQPoller.register", "name": "register", "type": null}}, "unregister": {".class": "SymbolTableNode", "kind": "Mdef", "node": {".class": "FuncDef", "arg_kinds": [0, 0], "arg_names": ["self", "fd"], "flags": [], "fullname": "zmq.eventloop._deprecated.ZMQPoller.unregister", "name": "unregister", "type": null}}}, "tuple_type": null, "type_vars": [], "typeddict_type": null}}, "__doc__": {".class": "SymbolTableNode", "kind": "Gdef", "node": {".class": "Var", "flags": ["is_ready"], "fullname": "zmq.eventloop._deprecated.__doc__", "name": "__doc__", "type": "builtins.str"}}, "__file__": {".class": "SymbolTableNode", "kind": "Gdef", "node": {".class": "Var", "flags": ["is_ready"], "fullname": "zmq.eventloop._deprecated.__file__", "name": "__file__", "type": "builtins.str"}}, "__name__": {".class": "SymbolTableNode", "kind": "Gdef", "node": {".class": "Var", "flags": ["is_ready"], "fullname": "zmq.eventloop._deprecated.__name__", "name": "__name__", "type": "builtins.str"}}, "__package__": {".class": "SymbolTableNode", "kind": "Gdef", "node": {".class": "Var", "flags": ["is_ready"], "fullname": "zmq.eventloop._deprecated.__package__", "name": "__package__", "type": "builtins.str"}}, "absolute_import": {".class": "SymbolTableNode", "cross_ref": "__future__.absolute_import", "kind": "Gdef"}, "division": {".class": "SymbolTableNode", "cross_ref": "__future__.division", "kind": "Gdef"}, "gen_log": {".class": "SymbolTableNode", "cross_ref": "zmq.eventloop.minitornado.log.gen_log", "kind": "Gdef"}, "install": {".class": "SymbolTableNode", "kind": "Gdef", "node": {".class": "FuncDef", "arg_kinds": [], "arg_names": [], "flags": [], "fullname": "zmq.eventloop._deprecated.install", "name": "install", "type": null}}, "os": {".class": "SymbolTableNode", "cross_ref": "os", "kind": "Gdef"}, "time": {".class": "SymbolTableNode", "cross_ref": "time", "kind": "Gdef"}, "tornado": {".class": "SymbolTableNode", "cross_ref": "tornado", "kind": "Gdef"}, "tornado_version": {".class": "SymbolTableNode", "kind": "Gdef", "node": {".class": "Var", "flags": ["is_ready"], "fullname": "zmq.eventloop._deprecated.tornado_version", "name": "tornado_version", "type": {".class": "Instance", "args": [{".class": "AnyType", "missing_import_name": null, "source_any": null, "type_of_any": 4}], "type_ref": "builtins.tuple"}}}, "warnings": {".class": "SymbolTableNode", "cross_ref": "warnings", "kind": "Gdef"}, "with_statement": {".class": "SymbolTableNode", "cross_ref": "__future__.with_statement", "kind": "Gdef"}}, "path": "/Users/gmatteo/miniconda3/envs/env3.9/lib/python3.9/site-packages/zmq/eventloop/_deprecated.py"}