{".class":"MypyFile","_fullname":"mdformat._util","future_import_flags":["annotations"],"is_partial_stub_package":false,"is_stub":false,"names":{".class":"SymbolTable","Any":{".class":"SymbolTableNode","cross_ref":"typing.Any","kind":"Gdef"},"EMPTY_MAP":{".class":"SymbolTableNode","kind":"Gdef","node":{".class":"Var","flags":["is_ready","has_explicit_value"],"fullname":"mdformat._util.EMPTY_MAP","name":"EMPTY_MAP","type":{".class":"Instance","args":[{".class":"AnyType","missing_import_name":null,"source_any":null,"type_of_any":4},{".class":"AnyType","missing_import_name":null,"source_any":null,"type_of_any":4}],"type_ref":"types.MappingProxyType"}}},"Iterable":{".class":"SymbolTableNode","cross_ref":"typing.Iterable","kind":"Gdef"},"Literal":{".class":"SymbolTableNode","cross_ref":"typing.Literal","kind":"Gdef"},"Mapping":{".class":"SymbolTableNode","cross_ref":"typing.Mapping","kind":"Gdef"},"MappingProxyType":{".class":"SymbolTableNode","cross_ref":"types.MappingProxyType","kind":"Gdef"},"MarkdownIt":{".class":"SymbolTableNode","cross_ref":"markdown_it.main.MarkdownIt","kind":"Gdef"},"NULL_CTX":{".class":"SymbolTableNode","kind":"Gdef","node":{".class":"Var","flags":["is_inferred","has_explicit_value"],"fullname":"mdformat._util.NULL_CTX","name":"NULL_CTX","type":{".class":"Instance","args":[{".class":"NoneType"}],"type_ref":"contextlib.nullcontext"}}},"Path":{".class":"SymbolTableNode","cross_ref":"pathlib.Path","kind":"Gdef"},"RE_NEWLINES":{".class":"SymbolTableNode","kind":"Gdef","node":{".class":"Var","flags":["is_inferred","has_explicit_value"],"fullname":"mdformat._util.RE_NEWLINES","name":"RE_NEWLINES","type":{".class":"Instance","args":["builtins.str"],"type_ref":"re.Pattern"}}},"RendererHTML":{".class":"SymbolTableNode","cross_ref":"markdown_it.renderer.RendererHTML","kind":"Gdef"},"__annotations__":{".class":"SymbolTableNode","kind":"Gdef","node":{".class":"Var","flags":["is_ready"],"fullname":"mdformat._util.__annotations__","name":"__annotations__","type":{".class":"Instance","args":["builtins.str",{".class":"AnyType","missing_import_name":null,"source_any":null,"type_of_any":6}],"type_ref":"builtins.dict"}}},"__doc__":{".class":"SymbolTableNode","kind":"Gdef","node":{".class":"Var","flags":["is_ready"],"fullname":"mdformat._util.__doc__","name":"__doc__","type":"builtins.str"}},"__file__":{".class":"SymbolTableNode","kind":"Gdef","node":{".class":"Var","flags":["is_ready"],"fullname":"mdformat._util.__file__","name":"__file__","type":"builtins.str"}},"__name__":{".class":"SymbolTableNode","kind":"Gdef","node":{".class":"Var","flags":["is_ready"],"fullname":"mdformat._util.__name__","name":"__name__","type":"builtins.str"}},"__package__":{".class":"SymbolTableNode","kind":"Gdef","node":{".class":"Var","flags":["is_ready"],"fullname":"mdformat._util.__package__","name":"__package__","type":"builtins.str"}},"annotations":{".class":"SymbolTableNode","cross_ref":"__future__.annotations","kind":"Gdef"},"atomic_write":{".class":"SymbolTableNode","kind":"Gdef","node":{".class":"FuncDef","abstract_status":0,"arg_kinds":[0,0,0],"arg_names":["path","text","newline"],"dataclass_transform_spec":null,"flags":[],"fullname":"mdformat._util.atomic_write","name":"atomic_write","type":{".class":"CallableType","arg_kinds":[0,0,0],"arg_names":["path","text","newline"],"arg_types":["pathlib.Path","builtins.str","builtins.str"],"bound_args":[],"def_extras":{"first_arg":null},"fallback":"builtins.function","from_concatenate":false,"implicit":false,"is_ellipsis_args":false,"name":"atomic_write","ret_type":{".class":"NoneType"},"type_guard":null,"unpack_kwargs":false,"variables":[]}}},"build_mdit":{".class":"SymbolTableNode","kind":"Gdef","node":{".class":"FuncDef","abstract_status":0,"arg_kinds":[0,5,5,5],"arg_names":["renderer_cls","mdformat_opts","extensions","codeformatters"],"dataclass_transform_spec":null,"flags":[],"fullname":"mdformat._util.build_mdit","name":"build_mdit","type":{".class":"CallableType","arg_kinds":[0,5,5,5],"arg_names":["renderer_cls","mdformat_opts","extensions","codeformatters"],"arg_types":[{".class":"AnyType","missing_import_name":null,"source_any":null,"type_of_any":2},{".class":"Instance","args":["builtins.str",{".class":"AnyType","missing_import_name":null,"source_any":null,"type_of_any":2}],"type_ref":"typing.Mapping"},{".class":"Instance","args":["builtins.str"],"type_ref":"typing.Iterable"},{".class":"Instance","args":["builtins.str"],"type_ref":"typing.Iterable"}],"bound_args":[],"def_extras":{"first_arg":null},"fallback":"builtins.function","from_concatenate":false,"implicit":false,"is_ellipsis_args":false,"name":"build_mdit","ret_type":"markdown_it.main.MarkdownIt","type_guard":null,"unpack_kwargs":false,"variables":[]}}},"detect_newline_type":{".class":"SymbolTableNode","kind":"Gdef","node":{".class":"FuncDef","abstract_status":0,"arg_kinds":[0,0],"arg_names":["md","eol_setting"],"dataclass_transform_spec":null,"flags":[],"fullname":"mdformat._util.detect_newline_type","name":"detect_newline_type","type":{".class":"CallableType","arg_kinds":[0,0],"arg_names":["md","eol_setting"],"arg_types":["builtins.str","builtins.str"],"bound_args":[],"def_extras":{"first_arg":null},"fallback":"builtins.function","from_concatenate":false,"implicit":false,"is_ellipsis_args":false,"name":"detect_newline_type","ret_type":{".class":"UnionType","items":[{".class":"LiteralType","fallback":"builtins.str","value":"\n"},{".class":"LiteralType","fallback":"builtins.str","value":"\r\n"}]},"type_guard":null,"unpack_kwargs":false,"variables":[]}}},"is_md_equal":{".class":"SymbolTableNode","kind":"Gdef","node":{".class":"FuncDef","abstract_status":0,"arg_kinds":[0,0,5,5,5],"arg_names":["md1","md2","options","extensions","codeformatters"],"dataclass_transform_spec":null,"flags":[],"fullname":"mdformat._util.is_md_equal","name":"is_md_equal","type":{".class":"CallableType","arg_kinds":[0,0,5,5,5],"arg_names":["md1","md2","options","extensions","codeformatters"],"arg_types":["builtins.str","builtins.str",{".class":"Instance","args":["builtins.str",{".class":"AnyType","missing_import_name":null,"source_any":null,"type_of_any":2}],"type_ref":"typing.Mapping"},{".class":"Instance","args":["builtins.str"],"type_ref":"typing.Iterable"},{".class":"Instance","args":["builtins.str"],"type_ref":"typing.Iterable"}],"bound_args":[],"def_extras":{"first_arg":null},"fallback":"builtins.function","from_concatenate":false,"implicit":false,"is_ellipsis_args":false,"name":"is_md_equal","ret_type":"builtins.bool","type_guard":null,"unpack_kwargs":false,"variables":[]}}},"mdformat":{".class":"SymbolTableNode","cross_ref":"mdformat","kind":"Gdef"},"nullcontext":{".class":"SymbolTableNode","cross_ref":"contextlib.nullcontext","kind":"Gdef"},"os":{".class":"SymbolTableNode","cross_ref":"os","kind":"Gdef"},"re":{".class":"SymbolTableNode","cross_ref":"re","kind":"Gdef"},"tempfile":{".class":"SymbolTableNode","cross_ref":"tempfile","kind":"Gdef"}},"path":"/home/romain/inria/cat_root/catleg/.tox/type/lib/python3.11/site-packages/mdformat/_util.py"}